ChatLoader.py
Errors.py
Extra.py
MessageProcessor.py
Reply.py
Shared_Resources.py
Storage.py
_Humanize.py
_Media.py
directory.py
login.py
selector_config.py
unread_handler.py
BrowserManager/__init__.py
test/__init__.py
test/decorator.py
test/play.py
test/sqltest.py
test/testmodule.py
tweakio_sdk-0.1.4.dist-info/licenses/LICENSE
tweakio_sdk-0.1.4.dist-info/METADATA
tweakio_sdk-0.1.4.dist-info/WHEEL
tweakio_sdk-0.1.4.dist-info/top_level.txt
tweakio_sdk-0.1.4.dist-info/RECORD
