Metadata-Version: 2.4
Name: tweakio-SDK
Version: 0.1.4
Summary: High-performance, anti-detection WhatsApp automation SDK. Features async SQLite storage, rate limiting, and human-like interaction loops.
Author: Rohit
Author-email: 
License: MIT
Project-URL: Homepage, https://github.com/Start-Tweakio/Tweakio-SDK
Project-URL: Bug Tracker, https://github.com/Start-Tweakio/Tweakio-SDK/issues
Classifier: Programming Language :: Python :: 3
Classifier: Operating System :: OS Independent
Requires-Python: >=3.8
License-File: LICENSE
Requires-Dist: playwright>=1.40.0
Requires-Dist: camoufox>=0.3.5
Requires-Dist: browserforge>=1.0.0
Requires-Dist: platformdirs>=4.0.0
Requires-Dist: colorlog>=6.0.0
Dynamic: license-file
Dynamic: requires-python
